LICENSE
MANIFEST.in
README.rst
setup.py
django_ratelimit9.egg-info/PKG-INFO
django_ratelimit9.egg-info/SOURCES.txt
django_ratelimit9.egg-info/dependency_links.txt
django_ratelimit9.egg-info/requires.txt
django_ratelimit9.egg-info/top_level.txt
ratelimit9/__init__.py
ratelimit9/forms.py
ratelimit9/mixins.py