Metadata-Version: 1.1
Name: django-ratelimit9
Version: 0.1
Summary: App that dynamically adds reCAPTCHA field to forms when user exceeds the rate limit
Home-page: https://github.com/9dev/django-ratelimit9
Author: 9dev
Author-email: 9devmail@gmail.com
License: MIT License
Platform: UNKNOWN
Classifier: Environment :: Web Environment
Classifier: Framework :: Django
Classifier: Intended Audience :: Developers
Classifier: License :: OSI Approved :: MIT License
Classifier: Operating System :: OS Independent
Classifier: Programming Language :: Python
Classifier: Programming Language :: Python :: 2.7
Classifier: Topic :: Internet :: WWW/HTTP
Classifier: Topic :: Internet :: WWW/HTTP :: Dynamic Content
